{"id":"1z0ttpmpktr0o5walg267vb","title":"Gparted","desc":"","updated":1653569050991,"created":1653569050991,"custom":{},"fname":"devlog.gparted","type":"note","vault":{"fsPath":".","selfContained":true,"name":"Dendron"},"contentHash":"6d172bd00c3f6fe58d9370f4570beed9","links":[{"from":{"fname":"areas.devops","vaultName":"Dendron"},"type":"backlink","position":{"start":{"line":66,"column":7,"offset":2265},"end":{"line":66,"column":25,"offset":2283},"indent":[]},"value":"devlog.gparted","alias":"devlog.gparted"},{"from":{"fname":"devlog.mount","vaultName":"Dendron"},"type":"backlink","position":{"start":{"line":108,"column":11,"offset":3568},"end":{"line":108,"column":29,"offset":3586},"indent":[]},"value":"devlog.gparted","alias":"devlog.gparted"}],"anchors":{},"children":[],"parent":"9gtn7g40cvqui0sifl1s7t5","data":{}}
