{"id":"2f0y6nf9jyf4erht10sycp7","title":"The Scout Mindset","desc":"","updated":1652798258265,"created":"2022-02-23T00:00:00.000Z","tags":["books"],"custom":{},"fname":"resources.books.the scout mindset","type":"note","vault":{"fsPath":".","selfContained":true,"name":"Dendron"},"contentHash":"47263b6c5d890ca9c60696c27dadf342","links":[{"type":"frontmatterTag","from":{"fname":"resources.books.the scout mindset","id":"2f0y6nf9jyf4erht10sycp7","vaultName":"Dendron"},"value":"tags.books","alias":"books","xvault":false,"to":{"fname":"tags.books"}},{"type":"wiki","from":{"fname":"resources.books.the scout mindset","id":"2f0y6nf9jyf4erht10sycp7","vaultName":"Dendron"},"value":"Rationality","alias":"Rationality","position":{"start":{"line":3,"column":10,"offset":39},"end":{"line":3,"column":25,"offset":54},"indent":[]},"xvault":false,"sameFile":false,"to":{"fname":"Rationality"}},{"type":"wiki","from":{"fname":"resources.books.the scout mindset","id":"2f0y6nf9jyf4erht10sycp7","vaultName":"Dendron"},"value":"Julia Galef","alias":"Julia Galef","position":{"start":{"line":4,"column":16,"offset":70},"end":{"line":4,"column":31,"offset":85},"indent":[]},"xvault":false,"sameFile":false,"to":{"fname":"Julia Galef"}}],"anchors":{"bucket-of-coping-strategies":{"type":"header","text":"Bucket of coping strategies","value":"bucket-of-coping-strategies","line":524,"column":0,"depth":2},"the-psychological-effect-of-expecting-variance":{"type":"header","text":"The psychological effect of expecting variance","value":"the-psychological-effect-of-expecting-variance","line":668,"column":0,"depth":2},"two-types-of-confidence":{"type":"header","text":"Two types of confidence","value":"two-types-of-confidence","line":722,"column":0,"depth":2},"two-kinds-of-uncertainty":{"type":"header","text":"Two kinds of uncertainty","value":"two-kinds-of-uncertainty","line":750,"column":0,"depth":2}},"children":[],"parent":"uab1n5o4isagyzs8tv79uq5","data":{}}
