{"id":"3fw1oows02l75rautccfl32","title":"Meconium","desc":"","updated":1653240411193,"created":"2022-04-19T00:00:00.000Z","tags":["TIL"],"custom":{},"fname":"archive.meconium","type":"note","vault":{"fsPath":".","selfContained":true,"name":"Dendron"},"contentHash":"9ef71ecf2ef846eaf9c03428925ac92c","links":[{"type":"frontmatterTag","from":{"fname":"archive.meconium","id":"3fw1oows02l75rautccfl32","vaultName":"Dendron"},"value":"tags.TIL","alias":"TIL","xvault":false,"to":{"fname":"tags.TIL"}},{"type":"wiki","from":{"fname":"archive.meconium","id":"3fw1oows02l75rautccfl32","vaultName":"Dendron"},"value":"areas.biology","alias":"areas.biology","position":{"start":{"line":2,"column":10,"offset":10},"end":{"line":2,"column":27,"offset":27},"indent":[]},"xvault":false,"sameFile":false,"to":{"fname":"areas.biology"}}],"anchors":{"what-is-meconium":{"type":"header","text":"What Is Meconium?","value":"what-is-meconium","line":14,"column":0,"depth":3},"what-is-meconium-aspiration-syndrome":{"type":"header","text":"What Is Meconium Aspiration Syndrome?","value":"what-is-meconium-aspiration-syndrome","line":18,"column":0,"depth":3},"what-causes-meconium-aspiration-syndrome":{"type":"header","text":"What Causes Meconium Aspiration Syndrome?","value":"what-causes-meconium-aspiration-syndrome","line":28,"column":0,"depth":3}},"children":[],"parent":"0yay2om15bsg2li2p6qgux7","data":{}}
