{"id":"3lf2ft5b3uosgqjirjgsvv6","title":"O Hell, to choose love by another’s eyes","desc":"","updated":1654319905208,"created":"2022-04-19T00:00:00.000Z","tags":["quotes"],"custom":{},"fname":"swipes.quotes.o hell, to choose love by another’s eyes","type":"note","vault":{"fsPath":".","selfContained":true,"name":"Dendron"},"contentHash":"e4dcd60c6da4ef7a071412d16dd38b5d","links":[{"type":"frontmatterTag","from":{"fname":"swipes.quotes.o hell, to choose love by another’s eyes","id":"3lf2ft5b3uosgqjirjgsvv6","vaultName":"Dendron"},"value":"tags.quotes","alias":"quotes","xvault":false,"to":{"fname":"tags.quotes"}},{"type":"wiki","from":{"fname":"swipes.quotes.o hell, to choose love by another’s eyes","id":"3lf2ft5b3uosgqjirjgsvv6","vaultName":"Dendron"},"value":"William Shakespeare","alias":"William Shakespeare","position":{"start":{"line":2,"column":52,"offset":52},"end":{"line":2,"column":75,"offset":75},"indent":[]},"xvault":false,"sameFile":false,"to":{"fname":"William Shakespeare"}}],"anchors":{},"children":[],"parent":"5uu8gws4omegsnoxq7ny75f","data":{}}
