{"id":"3y5fhwf5i2i1ovyrvpwolcl","title":"Zero to One Notes on Startups, or How to Build the Future","desc":"","updated":1652786940482,"created":1652786940482,"tags":["articles"],"custom":{},"fname":"inbox.zero to one notes on startups, or how to build the future","type":"note","vault":{"fsPath":".","selfContained":true,"name":"Dendron"},"contentHash":"b31945850926ce840607bdd17898f693","links":[{"type":"frontmatterTag","from":{"fname":"inbox.zero to one notes on startups, or how to build the future","id":"3y5fhwf5i2i1ovyrvpwolcl","vaultName":"Dendron"},"value":"tags.articles","alias":"articles","xvault":false,"to":{"fname":"tags.articles"}}],"anchors":{"zero-to-one-notes-on-startups-or-how-to-build-the-future":{"type":"header","text":"Zero to One: Notes on Startups, or How to Build the Future","value":"zero-to-one-notes-on-startups-or-how-to-build-the-future","line":10,"column":0,"depth":1},"notes-on-questions-to-ask-yourself-in-the-project-discovery-phase":{"type":"header","text":"Notes on questions to ask yourself in the project discovery phase","value":"notes-on-questions-to-ask-yourself-in-the-project-discovery-phase","line":18,"column":0,"depth":3},"notes-on-lessons-learnt":{"type":"header","text":"Notes on lessons learnt","value":"notes-on-lessons-learnt","line":50,"column":0,"depth":3},"a-small-favor":{"type":"header","text":"A small favor","value":"a-small-favor","line":78,"column":0,"depth":5},"follow-along":{"type":"header","text":"Follow along","value":"follow-along","line":82,"column":0,"depth":5}},"children":[],"parent":"ftbd1hknsd3ocd7jao26tn3","data":{}}
