{"id":"8j230dwo5jnsjsgba30i342","title":"IPFIX","desc":"","updated":1656492375081,"created":1656492301042,"custom":{},"fname":"devlog.IPFIX","type":"note","vault":{"fsPath":".","selfContained":true,"name":"Dendron"},"contentHash":"4a98858a4ee2c220c7be9adb4170a182","links":[{"type":"wiki","from":{"fname":"devlog.IPFIX","id":"8j230dwo5jnsjsgba30i342","vaultName":"Dendron"},"value":"areas.networking","alias":"areas.networking","position":{"start":{"line":2,"column":10,"offset":10},"end":{"line":2,"column":30,"offset":30},"indent":[]},"xvault":false,"sameFile":false,"to":{"fname":"areas.networking"}},{"type":"wiki","from":{"fname":"devlog.IPFIX","id":"8j230dwo5jnsjsgba30i342","vaultName":"Dendron"},"value":"devlog.NetFlow","alias":"devlog.NetFlow","position":{"start":{"line":8,"column":238,"offset":441},"end":{"line":8,"column":256,"offset":459},"indent":[]},"xvault":false,"sameFile":false,"to":{"fname":"devlog.NetFlow"}},{"from":{"fname":"devlog.NetDevOps","vaultName":"Dendron"},"type":"backlink","position":{"start":{"line":24,"column":246,"offset":3526},"end":{"line":24,"column":262,"offset":3542},"indent":[]},"value":"devlog.IPFIX","alias":"devlog.IPFIX"}],"anchors":{},"children":[],"parent":"9gtn7g40cvqui0sifl1s7t5","data":{}}
