{"id":"97zl34x7d8uhfxyn4wi414z","title":"Parthenogenesis","desc":"","updated":1658257731333,"created":"2021-09-28T00:00:00.000Z","custom":{},"fname":"archive.parthenogenesis","type":"note","vault":{"fsPath":".","selfContained":true,"name":"Dendron"},"contentHash":"dcbf3d0d307afe42977da903f34a9dd7","links":[{"type":"wiki","from":{"fname":"archive.parthenogenesis","id":"97zl34x7d8uhfxyn4wi414z","vaultName":"Dendron"},"value":"areas.biology","alias":"areas.biology","position":{"start":{"line":2,"column":9,"offset":9},"end":{"line":2,"column":26,"offset":26},"indent":[]},"xvault":false,"sameFile":false,"to":{"fname":"areas.biology"}}],"anchors":{},"children":[],"parent":"0yay2om15bsg2li2p6qgux7","data":{}}
