{"id":"anwjeubm8osm12vcyzpep4h","title":"betwixt and between","desc":"","updated":1658258022574,"created":"2022-03-03T00:00:00.000Z","tags":["phrases"],"custom":{},"fname":"swipes.phrases.betwixt and between","type":"note","vault":{"fsPath":".","selfContained":true,"name":"Dendron"},"contentHash":"12a183620e7c7461cb62a721a78aa3e5","links":[{"type":"frontmatterTag","from":{"fname":"swipes.phrases.betwixt and between","id":"anwjeubm8osm12vcyzpep4h","vaultName":"Dendron"},"value":"tags.phrases","alias":"phrases","xvault":false,"to":{"fname":"tags.phrases"}}],"anchors":{},"children":[],"parent":"5xbqzzau09hrv1e73sncws8","data":{}}
