{"id":"bdcbx6s0su210pfy9ougthr","title":"Zen Habits","desc":"","updated":1652786940450,"created":1652786940450,"tags":["articles","webmark"],"custom":{},"fname":"inbox.zen habits","type":"note","vault":{"fsPath":".","selfContained":true,"name":"Dendron"},"contentHash":"e5eac34a0b423368540f1fecf920aa95","links":[{"type":"frontmatterTag","from":{"fname":"inbox.zen habits","id":"bdcbx6s0su210pfy9ougthr","vaultName":"Dendron"},"value":"tags.articles","alias":"articles","xvault":false,"to":{"fname":"tags.articles"}},{"type":"frontmatterTag","from":{"fname":"inbox.zen habits","id":"bdcbx6s0su210pfy9ougthr","vaultName":"Dendron"},"value":"tags.webmark","alias":"webmark","xvault":false,"to":{"fname":"tags.webmark"}},{"type":"wiki","from":{"fname":"inbox.zen habits","id":"bdcbx6s0su210pfy9ougthr","vaultName":"Dendron"},"value":"Habits","alias":"Habits","position":{"start":{"line":1,"column":10,"offset":9},"end":{"line":1,"column":20,"offset":19},"indent":[]},"xvault":false,"sameFile":false,"to":{"fname":"Habits"}}],"anchors":{"zen-habits":{"type":"header","text":"zen habits","value":"zen-habits","line":14,"column":0,"depth":1},"by-leo-babauta":{"type":"header","text":"By Leo Babauta","value":"by-leo-babauta","line":16,"column":0,"depth":4},"why-we-have-compulsive-habits":{"type":"header","text":"Why We Have Compulsive Habits","value":"why-we-have-compulsive-habits","line":26,"column":0,"depth":3},"remove-judgment-add-compassion":{"type":"header","text":"Remove Judgment, Add Compassion","value":"remove-judgment-add-compassion","line":43,"column":0,"depth":3},"persistent-patient-commitment":{"type":"header","text":"Persistent, Patient Commitment","value":"persistent-patient-commitment","line":53,"column":0,"depth":3},"change-your-environment":{"type":"header","text":"Change Your Environment","value":"change-your-environment","line":63,"column":0,"depth":3},"dont-do-it-alone":{"type":"header","text":"Don’t Do It Alone","value":"dont-do-it-alone","line":71,"column":0,"depth":3},"practice-awareness--the-powerful-pause":{"type":"header","text":"Practice Awareness & the Powerful Pause","value":"practice-awareness--the-powerful-pause","line":81,"column":0,"depth":3},"dont-stop":{"type":"header","text":"Don’t Stop","value":"dont-stop","line":93,"column":0,"depth":3}},"children":[],"parent":"ftbd1hknsd3ocd7jao26tn3","data":{}}
