{"id":"ifoh1rf14twk7kglsl46kz9","title":"CAN","desc":"","updated":1652817053257,"created":"2021-10-09T00:00:00.000Z","caption":"Campus Area Network","custom":{"caption":"Campus Area Network"},"fname":"devlog.campus area network","type":"note","vault":{"fsPath":".","selfContained":true,"name":"Dendron"},"contentHash":"5b4e17253a2509b1cf8b8c2cd4179b0e","links":[{"type":"wiki","from":{"fname":"devlog.campus area network","id":"ifoh1rf14twk7kglsl46kz9","vaultName":"Dendron"},"value":"areas.networking","alias":"areas.networking","position":{"start":{"line":2,"column":10,"offset":10},"end":{"line":2,"column":30,"offset":30},"indent":[]},"xvault":false,"sameFile":false,"to":{"fname":"areas.networking"}}],"anchors":{},"children":[],"parent":"9gtn7g40cvqui0sifl1s7t5","data":{}}
