{"id":"j1nrw1ewito7rj8yhhdoze3","title":"Red herring","desc":"","updated":1652817985235,"created":"2022-03-17T00:00:00.000Z","tags":["TIL"],"custom":{},"fname":"archive.red herring","type":"note","vault":{"fsPath":".","selfContained":true,"name":"Dendron"},"contentHash":"8a65f7aa51505a8469eaf453f181f405","links":[{"type":"frontmatterTag","from":{"fname":"archive.red herring","id":"j1nrw1ewito7rj8yhhdoze3","vaultName":"Dendron"},"value":"tags.TIL","alias":"TIL","xvault":false,"to":{"fname":"tags.TIL"}},{"type":"wiki","from":{"fname":"archive.red herring","id":"j1nrw1ewito7rj8yhhdoze3","vaultName":"Dendron"},"value":"areas.discourse","alias":"areas.discourse","position":{"start":{"line":2,"column":10,"offset":10},"end":{"line":2,"column":29,"offset":29},"indent":[]},"xvault":false,"sameFile":false,"to":{"fname":"areas.discourse"}}],"anchors":{},"children":[],"parent":"0yay2om15bsg2li2p6qgux7","data":{}}
