{"id":"lgr6a9u0liepdg62jw077wr","title":"Ideas","desc":"","updated":1652618250591,"created":1652618250591,"custom":{},"fname":"tags.ideas","type":"note","vault":{"fsPath":".","selfContained":true,"name":"Dendron"},"contentHash":"3771bdd3a05143f45fe050931dfb92c6","links":[{"from":{"fname":"archive.Strong Opinions, Weakly Held","vaultName":"Dendron"},"type":"backlink","value":"tags.ideas","alias":"ideas"},{"from":{"fname":"slipbox.epistemic rationality","vaultName":"Dendron"},"type":"backlink","value":"tags.ideas","alias":"ideas"},{"from":{"fname":"slipbox.instrumental rationality","vaultName":"Dendron"},"type":"backlink","value":"tags.ideas","alias":"ideas"},{"from":{"fname":"slipbox.save your thefts for later","vaultName":"Dendron"},"type":"backlink","value":"tags.ideas","alias":"ideas"},{"from":{"fname":"slipbox.atheism vs. religion","vaultName":"Dendron"},"type":"backlink","value":"tags.ideas","alias":"ideas"}],"anchors":{},"children":[],"parent":"vtvk3bi6o72w58oima9xzf3","data":{}}
