{"id":"qcaw5ht4vcnucydq104gh7v","title":"Build Automation","desc":"","updated":1654758092310,"created":1654366736028,"custom":{},"fname":"devlog.build automation","type":"note","vault":{"fsPath":".","selfContained":true,"name":"Dendron"},"contentHash":"c994d41ec93a9046b5aa9f4918dc18f8","links":[{"type":"wiki","from":{"fname":"devlog.build automation","id":"qcaw5ht4vcnucydq104gh7v","vaultName":"Dendron"},"value":"devlog.jenkins","alias":"devlog.jenkins","position":{"start":{"line":2,"column":12,"offset":12},"end":{"line":2,"column":30,"offset":30},"indent":[]},"xvault":false,"sameFile":false,"to":{"fname":"devlog.jenkins"}},{"type":"wiki","from":{"fname":"devlog.build automation","id":"qcaw5ht4vcnucydq104gh7v","vaultName":"Dendron"},"value":"devlog.CI⁄CD pipeline","alias":"devlog.CI⁄CD pipeline","position":{"start":{"line":10,"column":47,"offset":372},"end":{"line":10,"column":72,"offset":397},"indent":[]},"xvault":false,"sameFile":false,"to":{"fname":"devlog.CI⁄CD pipeline"}},{"type":"wiki","from":{"fname":"devlog.build automation","id":"qcaw5ht4vcnucydq104gh7v","vaultName":"Dendron"},"value":"devlog.jenkins","alias":"devlog.jenkins","position":{"start":{"line":12,"column":70,"offset":468},"end":{"line":12,"column":88,"offset":486},"indent":[]},"xvault":false,"sameFile":false,"to":{"fname":"devlog.jenkins"}},{"type":"wiki","from":{"fname":"devlog.build automation","id":"qcaw5ht4vcnucydq104gh7v","vaultName":"Dendron"},"value":"devlog.nexus","alias":"devlog.nexus","position":{"start":{"line":27,"column":55,"offset":922},"end":{"line":27,"column":71,"offset":938},"indent":[]},"xvault":false,"sameFile":false,"to":{"fname":"devlog.nexus"}},{"type":"wiki","from":{"fname":"devlog.build automation","id":"qcaw5ht4vcnucydq104gh7v","vaultName":"Dendron"},"value":"devlog.Artifact Repository","alias":"devlog.Artifact Repository","position":{"start":{"line":38,"column":11,"offset":1320},"end":{"line":38,"column":41,"offset":1350},"indent":[]},"xvault":false,"sameFile":false,"to":{"fname":"devlog.Artifact Repository"}},{"type":"wiki","from":{"fname":"devlog.build automation","id":"qcaw5ht4vcnucydq104gh7v","vaultName":"Dendron"},"value":"devlog.path","alias":"$PATH","position":{"start":{"line":44,"column":57,"offset":1509},"end":{"line":44,"column":78,"offset":1530},"indent":[]},"xvault":false,"sameFile":false,"to":{"fname":"devlog.path"}},{"type":"wiki","from":{"fname":"devlog.build automation","id":"qcaw5ht4vcnucydq104gh7v","vaultName":"Dendron"},"value":"devlog.environment variable","alias":"environment variable","position":{"start":{"line":45,"column":25,"offset":1583},"end":{"line":45,"column":77,"offset":1635},"indent":[]},"xvault":false,"sameFile":false,"to":{"fname":"devlog.environment variable"}},{"type":"wiki","from":{"fname":"devlog.build automation","id":"qcaw5ht4vcnucydq104gh7v","vaultName":"Dendron"},"value":"devlog.maven","alias":"devlog.maven","position":{"start":{"line":48,"column":11,"offset":1737},"end":{"line":48,"column":27,"offset":1753},"indent":[]},"xvault":false,"sameFile":false,"to":{"fname":"devlog.maven"}},{"type":"wiki","from":{"fname":"devlog.build automation","id":"qcaw5ht4vcnucydq104gh7v","vaultName":"Dendron"},"value":"devlog.gradle","alias":"devlog.gradle","position":{"start":{"line":58,"column":11,"offset":2232},"end":{"line":58,"column":28,"offset":2249},"indent":[]},"xvault":false,"sameFile":false,"to":{"fname":"devlog.gradle"}},{"type":"wiki","from":{"fname":"devlog.build automation","id":"qcaw5ht4vcnucydq104gh7v","vaultName":"Dendron"},"value":"devlog.javascript","alias":"devlog.javascript","position":{"start":{"line":75,"column":13,"offset":3216},"end":{"line":75,"column":34,"offset":3237},"indent":[]},"xvault":false,"sameFile":false,"to":{"fname":"devlog.javascript"}},{"type":"wiki","from":{"fname":"devlog.build automation","id":"qcaw5ht4vcnucydq104gh7v","vaultName":"Dendron"},"value":"devlog.nodejs","alias":"devlog.nodejs","position":{"start":{"line":75,"column":37,"offset":3240},"end":{"line":75,"column":54,"offset":3257},"indent":[]},"xvault":false,"sameFile":false,"to":{"fname":"devlog.nodejs"}},{"type":"wiki","from":{"fname":"devlog.build automation","id":"qcaw5ht4vcnucydq104gh7v","vaultName":"Dendron"},"value":"devlog.webpack","alias":"devlog.webpack","position":{"start":{"line":94,"column":27,"offset":4276},"end":{"line":94,"column":45,"offset":4294},"indent":[]},"xvault":false,"sameFile":false,"to":{"fname":"devlog.webpack"}},{"type":"wiki","from":{"fname":"devlog.build automation","id":"qcaw5ht4vcnucydq104gh7v","vaultName":"Dendron"},"value":"devlog.curl","alias":"devlog.curl","position":{"start":{"line":100,"column":41,"offset":4534},"end":{"line":100,"column":56,"offset":4549},"indent":[]},"xvault":false,"sameFile":false,"to":{"fname":"devlog.curl"}},{"type":"wiki","from":{"fname":"devlog.build automation","id":"qcaw5ht4vcnucydq104gh7v","vaultName":"Dendron"},"value":"devlog.wget","alias":"devlog.wget","position":{"start":{"line":100,"column":62,"offset":4555},"end":{"line":100,"column":77,"offset":4570},"indent":[]},"xvault":false,"sameFile":false,"to":{"fname":"devlog.wget"}},{"type":"wiki","from":{"fname":"devlog.build automation","id":"qcaw5ht4vcnucydq104gh7v","vaultName":"Dendron"},"value":"devlog.Docker","alias":"devlog.Docker","position":{"start":{"line":102,"column":10,"offset":4596},"end":{"line":102,"column":27,"offset":4613},"indent":[]},"xvault":false,"sameFile":false,"to":{"fname":"devlog.Docker"}},{"type":"wiki","from":{"fname":"devlog.build automation","id":"qcaw5ht4vcnucydq104gh7v","vaultName":"Dendron"},"value":"devlog.CI⁄CD pipeline","alias":"CI/CD Pipeline","position":{"start":{"line":110,"column":43,"offset":5110},"end":{"line":110,"column":83,"offset":5150},"indent":[]},"xvault":false,"sameFile":false,"to":{"fname":"devlog.CI⁄CD pipeline"}},{"type":"wiki","from":{"fname":"devlog.build automation","id":"qcaw5ht4vcnucydq104gh7v","vaultName":"Dendron"},"value":"devlog.nexus","alias":"devlog.nexus","position":{"start":{"line":112,"column":11,"offset":5164},"end":{"line":112,"column":27,"offset":5180},"indent":[]},"xvault":false,"sameFile":false,"to":{"fname":"devlog.nexus"}},{"from":{"fname":"areas.devops","vaultName":"Dendron"},"type":"backlink","position":{"start":{"line":144,"column":43,"offset":4295},"end":{"line":144,"column":70,"offset":4322},"indent":[]},"value":"devlog.build automation","alias":"devlog.build automation"},{"from":{"fname":"devlog.Artifact Repository","vaultName":"Dendron"},"type":"backlink","position":{"start":{"line":2,"column":1,"offset":1},"end":{"line":2,"column":67,"offset":67},"indent":[]},"value":"devlog.build automation"},{"from":{"fname":"devlog.devops interview questions","vaultName":"Dendron"},"type":"backlink","position":{"start":{"line":274,"column":1,"offset":12569},"end":{"line":274,"column":86,"offset":12654},"indent":[]},"value":"devlog.build automation"},{"from":{"fname":"devlog.jenkins","vaultName":"Dendron"},"type":"backlink","position":{"start":{"line":2,"column":127,"offset":127},"end":{"line":2,"column":154,"offset":154},"indent":[]},"value":"devlog.build automation","alias":"devlog.build automation"},{"from":{"fname":"devlog.nexus","vaultName":"Dendron"},"type":"backlink","position":{"start":{"line":15,"column":64,"offset":904},"end":{"line":15,"column":91,"offset":931},"indent":[]},"value":"devlog.build automation","alias":"devlog.build automation"},{"from":{"fname":"devlog.prometheus","vaultName":"Dendron"},"type":"backlink","position":{"start":{"line":62,"column":134,"offset":3332},"end":{"line":62,"column":173,"offset":3371},"indent":[]},"value":"devlog.build automation","alias":"Build Tools"}],"anchors":{"build-automation":{"type":"header","text":"Build Automation","value":"build-automation","line":12,"column":0,"depth":2},"what-do-build-and-package-manager-tools-do":{"type":"header","text":"What do build and package manager tools do?","value":"what-do-build-and-package-manager-tools-do","line":26,"column":0,"depth":2},"artifacts":{"type":"header","text":"Artifacts","value":"artifacts","line":38,"column":0,"depth":2},"building-java-applications":{"type":"header","text":"Building Java Applications","value":"building-java-applications","line":46,"column":0,"depth":2},"managing-java-dependencies":{"type":"header","text":"Managing Java dependencies","value":"managing-java-dependencies","line":75,"column":0,"depth":2},"building-devlogjavascript--devlognodejs-project":{"type":"header","text":"Building devlog.javascript / devlog.nodejs project.","value":"building-devlogjavascript--devlognodejs-project","line":81,"column":0,"depth":2},"publishing-build-artifacts":{"type":"header","text":"Publishing build artifacts","value":"publishing-build-artifacts","line":103,"column":0,"depth":2},"enter-devlogdocker":{"type":"header","text":"Enter devlog.Docker","value":"enter-devlogdocker","line":108,"column":0,"depth":2}},"children":[],"parent":"9gtn7g40cvqui0sifl1s7t5","data":{}}
