{"id":"tsxltmyrrbf5nr68tc0ex6a","title":"DLP","desc":"","updated":1652622341968,"created":"2021-09-27T00:00:00.000Z","caption":"Data Leakage Prevention","custom":{"caption":"Data Leakage Prevention"},"fname":"devlog.dlp","type":"note","vault":{"fsPath":".","selfContained":true,"name":"Dendron"},"contentHash":"4ebdfa59701164de89a25fcb1bc2aa91","links":[{"type":"wiki","from":{"fname":"devlog.dlp","id":"tsxltmyrrbf5nr68tc0ex6a","vaultName":"Dendron"},"value":"External Storage","alias":"External Storage","position":{"start":{"line":3,"column":111,"offset":112},"end":{"line":3,"column":131,"offset":132},"indent":[]},"xvault":false,"sameFile":false,"to":{"fname":"External Storage"}}],"anchors":{},"children":[],"parent":"9gtn7g40cvqui0sifl1s7t5","data":{}}
