{"id":"wlc7khvl2q82nl4qenzbhzc","title":"A doctor can bury his mistakes, but an architect","desc":"","updated":1654320014594,"created":1654197209632,"tags":["quotes"],"custom":{},"fname":"swipes.quotes.A doctor can bury his mistakes, but an architect","type":"note","vault":{"fsPath":".","selfContained":true,"name":"Dendron"},"contentHash":"de5b40f074d8f12ace619a37869fed73","links":[{"type":"frontmatterTag","from":{"fname":"swipes.quotes.A doctor can bury his mistakes, but an architect","id":"wlc7khvl2q82nl4qenzbhzc","vaultName":"Dendron"},"value":"tags.quotes","alias":"quotes","xvault":false,"to":{"fname":"tags.quotes"}}],"anchors":{},"children":[],"parent":"5uu8gws4omegsnoxq7ny75f","data":{}}
