{"id":"ychqbayozz99d62demll2gt","title":"SMB","desc":"","updated":1656561102797,"created":20211011075236324,"caption":"Server Message Block","custom":{"caption":"Server Message Block"},"fname":"devlog.smb","type":"note","vault":{"fsPath":".","selfContained":true,"name":"Dendron"},"contentHash":"dc5d262824ea81441534238e44110278","links":[{"type":"wiki","from":{"fname":"devlog.smb","id":"ychqbayozz99d62demll2gt","vaultName":"Dendron"},"value":"devlog.NetBIOS","alias":"devlog.NetBIOS","position":{"start":{"line":4,"column":35,"offset":187},"end":{"line":4,"column":53,"offset":205},"indent":[]},"xvault":false,"sameFile":false,"to":{"fname":"devlog.NetBIOS"}},{"type":"wiki","from":{"fname":"devlog.smb","id":"ychqbayozz99d62demll2gt","vaultName":"Dendron"},"value":"devlog.NetBIOS","alias":"devlog.NetBIOS","position":{"start":{"line":4,"column":69,"offset":221},"end":{"line":4,"column":87,"offset":239},"indent":[]},"xvault":false,"sameFile":false,"to":{"fname":"devlog.NetBIOS"}}],"anchors":{},"children":[],"parent":"9gtn7g40cvqui0sifl1s7t5","data":{}}
