{"id":"zc6s7ns62mpszvjswr0oo7u","title":"Gratitude is not only the greatest of the virtues","desc":"","updated":1652716548095,"created":1652716548095,"tags":["quotes"],"custom":{},"fname":"swipes.quotes.gratitude is not only the greatest of the virtues","type":"note","vault":{"fsPath":".","selfContained":true,"name":"Dendron"},"contentHash":"aa8545d29550b2d2dbc0047564556e26","links":[{"type":"frontmatterTag","from":{"fname":"swipes.quotes.gratitude is not only the greatest of the virtues","id":"zc6s7ns62mpszvjswr0oo7u","vaultName":"Dendron"},"value":"tags.quotes","alias":"quotes","xvault":false,"to":{"fname":"tags.quotes"}},{"type":"wiki","from":{"fname":"swipes.quotes.gratitude is not only the greatest of the virtues","id":"zc6s7ns62mpszvjswr0oo7u","vaultName":"Dendron"},"value":"Cicero","alias":"Cicero","position":{"start":{"line":2,"column":90,"offset":90},"end":{"line":2,"column":100,"offset":100},"indent":[]},"xvault":false,"sameFile":false,"to":{"fname":"Cicero"}}],"anchors":{},"children":[],"parent":"5uu8gws4omegsnoxq7ny75f","data":{}}
